<TalentLetter>
  <Language-Family>
    <FamilyName>Einzelne Sprachen</FamilyName>
    <Language>
      <SpeakingName>Drachisch</SpeakingName>
      <SpeakingComplex>-21</SpeakingComplex>
      <FontName>Drakned</FontName>
      <FontComplex>15</FontComplex>
    </Language>
    <Language>
      <SpeakingName>Rssahh</SpeakingName>
      <SpeakingComplex>9</SpeakingComplex>
      <SpeakingComplexSecond>18</SpeakingComplexSecond>
      <FontName>Chrmk</FontName>
      <FontComplex>18</FontComplex>
    </Language>
    <Language>
      <SpeakingName></SpeakingName>
      <SpeakingComplex></SpeakingComplex>
      <FontName>Chuchas</FontName>
      <FontComplex>24</FontComplex>
    </Language>
    <Language>
      <SpeakingName>Trollisch</SpeakingName>
      <SpeakingComplex>15</SpeakingComplex>
      <FontName>Raumbilderschrift</FontName>
      <FontComplex>24</FontComplex>
    </Language>
    <Language>
      <SpeakingName>Goblinisch</SpeakingName>
      <SpeakingComplex>12</SpeakingComplex>
      <FontName></FontName>
      <FontComplex></FontComplex>
    </Language>
    <Language>
      <SpeakingName>Grolmisch</SpeakingName>
      <SpeakingComplex>6</SpeakingComplex>
      <SpeakingComplexSecond>17</SpeakingComplexSecond>
      <FontName></FontName>
      <FontComplex></FontComplex>
    </Language>
    <Language>
      <SpeakingName>Koboldisch</SpeakingName>
      <SpeakingComplex>-15</SpeakingComplex>
      <FontName></FontName>
      <FontComplex></FontComplex>
    </Language>
    <Language>
      <SpeakingName>Mohisch</SpeakingName>
      <SpeakingComplex>15</SpeakingComplex>
      <FontName></FontName>
      <FontComplex></FontComplex>
    </Language>
    <Language>
      <SpeakingName>Molochisch</SpeakingName>
      <SpeakingComplex>17</SpeakingComplex>
      <FontName></FontName>
      <FontComplex></FontComplex>
    </Language>
    <Language>
      <SpeakingName>Neckergesang</SpeakingName>
      <SpeakingComplex>24</SpeakingComplex>
      <FontName></FontName>
      <FontComplex></FontComplex>
    </Language>
    <Language>
      <SpeakingName>Nujuka</SpeakingName>
      <SpeakingComplex>15</SpeakingComplex>
      <FontName></FontName>
      <FontComplex></FontComplex>
    </Language>
    <Language>
      <SpeakingName>Z´Lit</SpeakingName>
      <SpeakingComplex>-17</SpeakingComplex>
      <FontName></FontName>
      <FontComplex></FontComplex>
    </Language>
    <Language>
      <SpeakingName>Zyklopäisch</SpeakingName>
      <SpeakingComplex>18</SpeakingComplex>
      <FontName>Kusliker Zeichen</FontName>
      <FontComplex>10</FontComplex>
    </Language>
    <Language>
      <SpeakingName>Rabensprache</SpeakingName>
      <SpeakingComplex>15</SpeakingComplex>
      <FontName>Kusliker Zeichen</FontName>
      <FontComplex>10</FontComplex>
    </Language>
    <Language>
      <SpeakingName></SpeakingName>
      <SpeakingComplex></SpeakingComplex>
      <FontName>Tulamidya</FontName>
      <FontComplex>14</FontComplex>
    </Language>
  </Language-Family>
</TalentLetter>